wiggler/__init__.py
wiggler/timelapse.py
wiggler-0.0.2.dist-info/METADATA
wiggler-0.0.2.dist-info/WHEEL
wiggler-0.0.2.dist-info/top_level.txt
wiggler-0.0.2.dist-info/RECORD
