Metadata-Version: 2.1
Name: wiggler
Version: 0.0.2
Summary: WiggleR - Desktop research unit for making controlled experiments
Author: Vincent Kranendonk
Keywords: python
